MANIFEST.in
license.txt
readme.rst
setup.cfg
setup.py
tox.ini
docs/Makefile
docs/changelog.rst
docs/conf.py
docs/index.rst
docs/license.rst
docs/quickstart.rst
docs/_static/theme_overrides.css
docs/_templates/layout.html
docs/references/broker.rst
docs/references/common.rst
docs/references/hbmqtt.rst
docs/references/hbmqtt_pub.rst
docs/references/hbmqtt_sub.rst
docs/references/index.rst
docs/references/mqttclient.rst
hbmqtt/__init__.py
hbmqtt/adapters.py
hbmqtt/broker.py
hbmqtt/client.py
hbmqtt/codecs.py
hbmqtt/errors.py
hbmqtt/session.py
hbmqtt/utils.py
hbmqtt/version.py
hbmqtt/mqtt/__init__.py
hbmqtt/mqtt/connack.py
hbmqtt/mqtt/connect.py
hbmqtt/mqtt/constants.py
hbmqtt/mqtt/disconnect.py
hbmqtt/mqtt/packet.py
hbmqtt/mqtt/pingreq.py
hbmqtt/mqtt/pingresp.py
hbmqtt/mqtt/puback.py
hbmqtt/mqtt/pubcomp.py
hbmqtt/mqtt/publish.py
hbmqtt/mqtt/pubrec.py
hbmqtt/mqtt/pubrel.py
hbmqtt/mqtt/suback.py
hbmqtt/mqtt/subscribe.py
hbmqtt/mqtt/unsuback.py
hbmqtt/mqtt/unsubscribe.py
hbmqtt/mqtt/protocol/__init__.py
hbmqtt/mqtt/protocol/broker_handler.py
hbmqtt/mqtt/protocol/client_handler.py
hbmqtt/mqtt/protocol/handler.py
hbmqtt/plugins/__init__.py
hbmqtt/plugins/authentication.py
hbmqtt/plugins/logging.py
hbmqtt/plugins/manager.py
hbmqtt/plugins/persistence.py
hbmqtt/plugins/topic_checking.py
hbmqtt/plugins/sys/__init__.py
hbmqtt/plugins/sys/broker.py
hbmqtt_master2.egg-info/PKG-INFO
hbmqtt_master2.egg-info/SOURCES.txt
hbmqtt_master2.egg-info/dependency_links.txt
hbmqtt_master2.egg-info/entry_points.txt
hbmqtt_master2.egg-info/requires.txt
hbmqtt_master2.egg-info/top_level.txt
samples/broker.py
samples/broker_acl.py
samples/broker_script.py
samples/broker_start.py
samples/broker_taboo.py
samples/client_keepalive.py
samples/client_publish.py
samples/client_publish_acl.py
samples/client_publish_ssl.py
samples/client_publish_ws.py
samples/client_subscribe.py
samples/client_subscribe_acl.py
samples/mosquitto.org.crt
samples/passwd
samples/publish.py
samples/subscribe.py
samples/t_sqlite.py
scripts/__init__.py
scripts/default_broker.yaml
scripts/default_client.yaml
scripts/pub_script.py
scripts/sub_script.py
tests/__init__.py
tests/mosquitto.org.crt
tests/test_broker.py
tests/test_client.py
tests/test_codecs.py
